odoo/addons/account_fiscal_position_product/README.rst
odoo/addons/account_fiscal_position_product/__init__.py
odoo/addons/account_fiscal_position_product/__manifest__.py
odoo/addons/account_fiscal_position_product/i18n/account_fiscal_position_product.pot
odoo/addons/account_fiscal_position_product/i18n/it.po
odoo/addons/account_fiscal_position_product/models/__init__.py
odoo/addons/account_fiscal_position_product/models/account_fiscal_position.py
odoo/addons/account_fiscal_position_product/models/account_fiscal_position_tax.py
odoo/addons/account_fiscal_position_product/readme/DESCRIPTION.rst
odoo/addons/account_fiscal_position_product/static/description/icon.png
odoo/addons/account_fiscal_position_product/static/description/index.html
odoo/addons/account_fiscal_position_product/tests/__init__.py
odoo/addons/account_fiscal_position_product/tests/test_fiscal_position_product.py
odoo/addons/account_fiscal_position_product/views/account_fiscal_position_views.xml
odoo12_addon_account_fiscal_position_product-12.0.1.0.0.99.dev3.dist-info/METADATA
odoo12_addon_account_fiscal_position_product-12.0.1.0.0.99.dev3.dist-info/WHEEL
odoo12_addon_account_fiscal_position_product-12.0.1.0.0.99.dev3.dist-info/top_level.txt
odoo12_addon_account_fiscal_position_product-12.0.1.0.0.99.dev3.dist-info/RECORD
