Metadata-Version: 2.1
Name: odoo12-addon-account-fiscal-position-product
Version: 12.0.1.0.0.99.dev3
Summary: Apply fiscal position only for configured products
Home-page: https://github.com/OCA/account-fiscal-rule/tree/12.0/account_fiscal_position_product
Author: TAKOBI, Odoo Community Association (OCA)
Author-email: support@odoo-community.org
License: AGPL-3
Platform: UNKNOWN
Classifier: Programming Language :: Python
Classifier: Framework :: Odoo
Classifier: Framework :: Odoo :: 12.0
Classifier: License :: OSI Approved :: GNU Affero General Public License v3
Classifier: Development Status :: 4 - Beta
Requires-Python: >=3.5
Requires-Dist: odoo <12.1dev,>=12.0a
